sparklepop/__init__.py
sparklepop-0.1.3.dist-info/METADATA
sparklepop-0.1.3.dist-info/WHEEL
sparklepop-0.1.3.dist-info/RECORD
